lark2ldap/__init__.py
lark2ldap/admin.py
lark2ldap/apps.py
lark2ldap/compat.py
lark2ldap/models.py
lark2ldap/serializers.py
lark2ldap/views.py
lark2ldap-0.1.0.dist-info/LICENSE
lark2ldap-0.1.0.dist-info/WHEEL
lark2ldap-0.1.0.dist-info/METADATA
lark2ldap-0.1.0.dist-info/RECORD
