Metadata-Version: 2.1
Name: lark2ldap
Version: 0.1.0
Summary: Django app,to sync feishu contacts to ldap.
Home-page: https://github.com/huangxy29/lark_to_ldap
License: MIT
Author: Huangxinyu
Author-email: huangxinyu.2991@gmail.com
Maintainer: Huangxinyu
Maintainer-email: huangxinyu.2991@gmail.com
Requires-Python: >=3.8,<4.0
Classifier: Development Status :: 4 - Beta
Classifier: Environment :: Web Environment
Classifier: Framework :: Django
Classifier: Framework :: Django :: 3.2
Classifier: Framework :: Django :: 4.0
Classifier: Framework :: Django :: 4.1
Classifier: License :: OSI Approved :: MIT License
Classifier: Operating System :: OS Independent
Classifier: Programming Language :: Python :: 3
Classifier: Programming Language :: Python :: 3.8
Classifier: Programming Language :: Python :: 3.9
Classifier: Programming Language :: Python :: 3.10
Classifier: Programming Language :: Python :: 3 :: Only
Classifier: Programming Language :: Python :: 3.10
Classifier: Programming Language :: Python :: 3.11
Classifier: Programming Language :: Python :: 3.8
Classifier: Programming Language :: Python :: 3.9
Requires-Dist: django (>=3.2,<5.0)
Project-URL: Documentation, https://github.com/huangxy29/lark_to_ldap
Project-URL: Repository, https://github.com/huangxy29/lark_to_ldap
